[{"symbol": "US", "price": 0.0427492, "change": 21.55284, "score": 90}, {"symbol": "DGB", "price": 0.00309213, "change": 14.75852, "score": 76}, {"symbol": "KAITO", "price": 0.862408, "change": 11.87311, "score": 65}, {"symbol": "RUNE", "price": 0.424637, "change": 1.40779, "score": 63}, {"symbol": "RAVE", "price": 0.321857, "change": 12.68252, "score": 63}, {"symbol": "RE", "price": 0.494669, "change": 1.22772, "score": 62}, {"symbol": "VIRTUAL", "price": 0.636024, "change": 2.70446, "score": 60}, {"symbol": "LDO", "price": 0.365442, "change": 2.36055, "score": 53}, {"symbol": "PLUME", "price": 0.01055103, "change": 1.39942, "score": 51}, {"symbol": "GALA", "price": 0.00209594, "change": 3.32928, "score": 49}]