[{"symbol": "HOT", "price": 0.00037216, "change": 16.43314, "score": 83}, {"symbol": "BTW", "price": 0.077068, "change": 18.17104, "score": 66}, {"symbol": "ULTIMA", "price": 2928.72, "change": 21.85041, "score": 66}, {"symbol": "SUN", "price": 0.01793327, "change": 5.06697, "score": 63}, {"symbol": "ANSEM", "price": 0.329536, "change": 0.08657, "score": 60}, {"symbol": "LIT", "price": 2.42, "change": 9.73199, "score": 56}, {"symbol": "RIF", "price": 0.109139, "change": 7.90903, "score": 49}, {"symbol": "XTZ", "price": 0.262853, "change": 8.65078, "score": 46}, {"symbol": "EIGEN", "price": 0.23974, "change": 3.82069, "score": 45}, {"symbol": "ALLO", "price": 0.357841, "change": 1.87713, "score": 43}]