[{"symbol": "ALLO", "price": 0.336539, "change": 45.30776, "score": 100}, {"symbol": "RE", "price": 0.692902, "change": 18.76795, "score": 98}, {"symbol": "MAGMA", "price": 0.53064, "change": 36.87416, "score": 76}, {"symbol": "FARTCOIN", "price": 0.159756, "change": 17.50548, "score": 74}, {"symbol": "SLX", "price": 0.503821, "change": 4.34786, "score": 69}, {"symbol": "XPL", "price": 0.095579, "change": 5.30018, "score": 68}, {"symbol": "ENA", "price": 0.076756, "change": 7.48705, "score": 67}, {"symbol": "MEGA", "price": 0.04909864, "change": 8.56401, "score": 67}, {"symbol": "W", "price": 0.01016797, "change": 8.79464, "score": 66}, {"symbol": "BERA", "price": 0.2182, "change": 6.99877, "score": 64}]